LICENSE
cosmicweb_music/__init__.py
cosmicweb_music/cosmICweb.py
cosmicweb_music/data_types.py
cosmicweb_music-0.3.0.dist-info/LICENSE
cosmicweb_music-0.3.0.dist-info/METADATA
cosmicweb_music-0.3.0.dist-info/WHEEL
cosmicweb_music-0.3.0.dist-info/entry_points.txt
cosmicweb_music-0.3.0.dist-info/RECORD
